TOPSIS_Sheramir_101803549/__init__.py
TOPSIS_Sheramir_101803549/__main__.py
TOPSIS_Sheramir_101803549-1.0.1.dist-info/LICENSE.txt
TOPSIS_Sheramir_101803549-1.0.1.dist-info/METADATA
TOPSIS_Sheramir_101803549-1.0.1.dist-info/WHEEL
TOPSIS_Sheramir_101803549-1.0.1.dist-info/top_level.txt
TOPSIS_Sheramir_101803549-1.0.1.dist-info/RECORD
