Metadata-Version: 2.1
Name: TOPSIS-Sheramir-101803549
Version: 1.0.1
Summary: This package is for TOPSIS
Home-page: UNKNOWN
Author: Sheramir
Author-email: sheramir51@gmail.com
License: UNKNOWN
Platform: UNKNOWN
Classifier: Programming Language :: Python :: 3
Classifier: License :: OSI Approved :: MIT License
Classifier: Operating System :: OS Independent
Requires-Dist: pandas
Requires-Dist: numpy (==1.19.3)
